aws_org_inventory.py
aws_org_inventory-0.5.2.post1.dist-info/entry_points.txt
aws_org_inventory-0.5.2.post1.dist-info/LICENSE
aws_org_inventory-0.5.2.post1.dist-info/WHEEL
aws_org_inventory-0.5.2.post1.dist-info/METADATA
aws_org_inventory-0.5.2.post1.dist-info/RECORD
