Metadata-Version: 2.1
Name: aws-org-inventory
Version: 0.5.2.post1
Summary:  Dumps to CSV all the resources in an organization's member accounts
Home-page: https://github.com/iainelder/aws-org-inventory
License: BSD-2-Clause
Author: Iain Samuel McLean Elder
Author-email: iain@isme.es
Requires-Python: >=3.8,<4.0
Classifier: License :: OSI Approved :: BSD License
Classifier: Programming Language :: Python :: 3
Classifier: Programming Language :: Python :: 3.10
Classifier: Programming Language :: Python :: 3.8
Classifier: Programming Language :: Python :: 3.9
Requires-Dist: boto-collator-client (>=0.1.1,<0.2.0)
Requires-Dist: boto3 (>=1.18.52,<2.0.0)
Requires-Dist: botocove (>=1.3.1,<2.0.0)
Requires-Dist: pandas (>=1.3.3,<2.0.0)
Project-URL: Botocove, https://github.com/connelldave/botocove
Project-URL: Repository, https://github.com/iainelder/aws-org-inventory
